[
{"name": "g16split.jpg", "parent_url": "https://tropic.ssec.wisc.edu/real-time/sal/g16split/", "page_title": "Index of /real-time/sal/g16split", "source_modified": "2026-02-15T21:30:00", "observation_time": "2026-02-15T21:00:00", "fetched_at": "2026-02-15T22:00:54.387347+00:00", "image_urls": ["https://tropic.ssec.wisc.edu/real-time/sal/g16split/g16split.jpg"], "etag": "\"80ee5-64ae38c8b8578\"", "raw_metadata": {"directory_path": "https://tropic.ssec.wisc.edu/real-time/sal/g16split", "last_modified_raw": "2026-02-15 21:30", "size_text": "516K", "size_bytes": 528384, "http_status": 200, "content_type": "image/jpeg", "content_length": 528101, "server": "Apache", "last_modified_http": "Sun, 15 Feb 2026 21:30:36 GMT"}, "spider_name": "cimss", "images": [{"url": "https://tropic.ssec.wisc.edu/real-time/sal/g16split/g16split.jpg", "path": "2026/02/15/21/202602152100_g16split.jpg", "checksum": "7b43460974dfb81d074f0d4394c5db5f", "status": "downloaded"}], "file_size_bytes": 528101, "file_format": "jpeg", "width": 1542, "height": 820, "mode": "RGB", "is_animated": false, "frame_count": 1},
{"name": "windNWATL.gif", "parent_url": "https://tropic.ssec.wisc.edu/real-time/wavetrak/domains/", "page_title": "Index of /real-time/wavetrak/domains", "source_modified": "2026-02-15T20:57:00", "observation_time": "2026-02-15T20:00:00", "fetched_at": "2026-02-15T22:00:54.984722+00:00", "image_urls": ["https://tropic.ssec.wisc.edu/real-time/wavetrak/domains/windNWATL.gif"], "etag": "\"568c4-64ae31527fc2c\"", "raw_metadata": {"directory_path": "https://tropic.ssec.wisc.edu/real-time/wavetrak/domains", "last_modified_raw": "2026-02-15 20:57", "size_text": "346K", "size_bytes": 354304, "http_status": 200, "content_type": "image/gif", "content_length": 354500, "server": "Apache", "last_modified_http": "Sun, 15 Feb 2026 20:57:13 GMT"}, "spider_name": "cimss", "images": [{"url": "https://tropic.ssec.wisc.edu/real-time/wavetrak/domains/windNWATL.gif", "path": "2026/02/15/20/202602152000_windNWATL.gif", "checksum": "2cfc3948240ef1673a4d2b176ed9e13a", "status": "downloaded"}], "file_size_bytes": 213653, "file_format": "jpeg", "width": 900, "height": 680, "mode": "RGB", "is_animated": false, "frame_count": 1},
{"name": "wg8conv.GIF", "parent_url": "https://tropic.ssec.wisc.edu/real-time/atlantic/winds/", "page_title": "Index of /real-time/atlantic/winds", "source_modified": "2026-02-15T21:44:00", "observation_time": "2026-02-15T21:00:00", "fetched_at": "2026-02-15T22:00:56.141735+00:00", "image_urls": ["https://tropic.ssec.wisc.edu/real-time/atlantic/winds/wg8conv.GIF"], "etag": "\"28b19-64ae3bddbadd1\"", "raw_metadata": {"directory_path": "https://tropic.ssec.wisc.edu/real-time/atlantic/winds", "last_modified_raw": "2026-02-15 21:44", "size_text": "163K", "size_bytes": 166912, "http_status": 200, "content_type": "image/gif", "content_length": 166681, "server": "Apache", "last_modified_http": "Sun, 15 Feb 2026 21:44:23 GMT"}, "spider_name": "cimss", "images": [{"url": "https://tropic.ssec.wisc.edu/real-time/atlantic/winds/wg8conv.GIF", "path": "2026/02/15/21/202602152100_wg8conv.GIF", "checksum": "2e8c06f96cd6646da3c08e85a5cd85b9", "status": "downloaded"}], "file_size_bytes": 156944, "file_format": "jpeg", "width": 900, "height": 680, "mode": "RGB", "is_animated": false, "frame_count": 1},
{"name": "wg8vor.GIF", "parent_url": "https://tropic.ssec.wisc.edu/real-time/atlantic/winds/", "page_title": "Index of /real-time/atlantic/winds", "source_modified": "2026-02-15T21:44:00", "observation_time": "2026-02-15T21:00:00", "fetched_at": "2026-02-15T22:00:56.152725+00:00", "image_urls": ["https://tropic.ssec.wisc.edu/real-time/atlantic/winds/wg8vor.GIF"], "etag": "\"350f9-64ae3bde3991d\"", "raw_metadata": {"directory_path": "https://tropic.ssec.wisc.edu/real-time/atlantic/winds", "last_modified_raw": "2026-02-15 21:44", "size_text": "212K", "size_bytes": 217088, "http_status": 200, "content_type": "image/gif", "content_length": 217337, "server": "Apache", "last_modified_http": "Sun, 15 Feb 2026 21:44:24 GMT"}, "spider_name": "cimss", "images": [{"url": "https://tropic.ssec.wisc.edu/real-time/atlantic/winds/wg8vor.GIF", "path": "2026/02/15/21/202602152100_wg8vor.GIF", "checksum": "6f94b17cb602c64f439d46c4fc6f919d", "status": "downloaded"}], "file_size_bytes": 145571, "file_format": "jpeg", "width": 960, "height": 680, "mode": "RGB", "is_animated": false, "frame_count": 1},
{"name": "wg8sht.GIF", "parent_url": "https://tropic.ssec.wisc.edu/real-time/atlantic/winds/", "page_title": "Index of /real-time/atlantic/winds", "source_modified": "2026-02-15T21:44:00", "observation_time": "2026-02-15T21:00:00", "fetched_at": "2026-02-15T22:00:56.147918+00:00", "image_urls": ["https://tropic.ssec.wisc.edu/real-time/atlantic/winds/wg8sht.GIF"], "etag": "\"322c2-64ae3bde166a0\"", "raw_metadata": {"directory_path": "https://tropic.ssec.wisc.edu/real-time/atlantic/winds", "last_modified_raw": "2026-02-15 21:44", "size_text": "201K", "size_bytes": 205824, "http_status": 200, "content_type": "image/gif", "content_length": 205506, "server": "Apache", "last_modified_http": "Sun, 15 Feb 2026 21:44:23 GMT"}, "spider_name": "cimss", "images": [{"url": "https://tropic.ssec.wisc.edu/real-time/atlantic/winds/wg8sht.GIF", "path": "2026/02/15/21/202602152100_wg8sht.GIF", "checksum": "3095cddd00dda5a02fcd7b86585a40e1", "status": "downloaded"}], "file_size_bytes": 221518, "file_format": "jpeg", "width": 960, "height": 680, "mode": "RGB", "is_animated": false, "frame_count": 1},
{"name": "wg8shr.GIF", "parent_url": "https://tropic.ssec.wisc.edu/real-time/atlantic/winds/", "page_title": "Index of /real-time/atlantic/winds", "source_modified": "2026-02-15T21:44:00", "observation_time": "2026-02-15T21:00:00", "fetched_at": "2026-02-15T22:00:56.147402+00:00", "image_urls": ["https://tropic.ssec.wisc.edu/real-time/atlantic/winds/wg8shr.GIF"], "etag": "\"23d59-64ae3bddfcc7b\"", "raw_metadata": {"directory_path": "https://tropic.ssec.wisc.edu/real-time/atlantic/winds", "last_modified_raw": "2026-02-15 21:44", "size_text": "143K", "size_bytes": 146432, "http_status": 200, "content_type": "image/gif", "content_length": 146777, "server": "Apache", "last_modified_http": "Sun, 15 Feb 2026 21:44:23 GMT"}, "spider_name": "cimss", "images": [{"url": "https://tropic.ssec.wisc.edu/real-time/atlantic/winds/wg8shr.GIF", "path": "2026/02/15/21/202602152100_wg8shr.GIF", "checksum": "8cea07032280506003434175f80d41b8", "status": "downloaded"}], "file_size_bytes": 222542, "file_format": "jpeg", "width": 900, "height": 680, "mode": "RGB", "is_animated": false, "frame_count": 1},
{"name": "wg8midshr.GIF", "parent_url": "https://tropic.ssec.wisc.edu/real-time/atlantic/winds/", "page_title": "Index of /real-time/atlantic/winds", "source_modified": "2026-02-15T21:44:00", "observation_time": "2026-02-15T21:00:00", "fetched_at": "2026-02-15T22:00:56.146921+00:00", "image_urls": ["https://tropic.ssec.wisc.edu/real-time/atlantic/winds/wg8midshr.GIF"], "etag": "\"38e27-64ae3bddfbcdb\"", "raw_metadata": {"directory_path": "https://tropic.ssec.wisc.edu/real-time/atlantic/winds", "last_modified_raw": "2026-02-15 21:44", "size_text": "228K", "size_bytes": 233472, "http_status": 200, "content_type": "image/gif", "content_length": 232999, "server": "Apache", "last_modified_http": "Sun, 15 Feb 2026 21:44:23 GMT"}, "spider_name": "cimss", "images": [{"url": "https://tropic.ssec.wisc.edu/real-time/atlantic/winds/wg8midshr.GIF", "path": "2026/02/15/21/202602152100_wg8midshr.GIF", "checksum": "f1a65826cdbec44777915c774ef0eb29", "status": "downloaded"}], "file_size_bytes": 209584, "file_format": "jpeg", "width": 960, "height": 680, "mode": "RGB", "is_animated": false, "frame_count": 1},
{"name": "wg8ir.GIF", "parent_url": "https://tropic.ssec.wisc.edu/real-time/atlantic/winds/", "page_title": "Index of /real-time/atlantic/winds", "source_modified": "2026-02-15T21:44:00", "observation_time": "2026-02-15T21:00:00", "fetched_at": "2026-02-15T22:00:56.146422+00:00", "image_urls": ["https://tropic.ssec.wisc.edu/real-time/atlantic/winds/wg8ir.GIF"], "etag": "\"2dae1-64ae3bddfad3b\"", "raw_metadata": {"directory_path": "https://tropic.ssec.wisc.edu/real-time/atlantic/winds", "last_modified_raw": "2026-02-15 21:44", "size_text": "183K", "size_bytes": 187392, "http_status": 200, "content_type": "image/gif", "content_length": 187105, "server": "Apache", "last_modified_http": "Sun, 15 Feb 2026 21:44:23 GMT"}, "spider_name": "cimss", "images": [{"url": "https://tropic.ssec.wisc.edu/real-time/atlantic/winds/wg8ir.GIF", "path": "2026/02/15/21/202602152100_wg8ir.GIF", "checksum": "e6354fe1cea34e9e7fe01fe0630df641", "status": "downloaded"}], "file_size_bytes": 207911, "file_format": "jpeg", "width": 900, "height": 680, "mode": "RGB", "is_animated": false, "frame_count": 1},
{"name": "wg8dvg.GIF", "parent_url": "https://tropic.ssec.wisc.edu/real-time/atlantic/winds/", "page_title": "Index of /real-time/atlantic/winds", "source_modified": "2026-02-15T21:44:00", "observation_time": "2026-02-15T21:00:00", "fetched_at": "2026-02-15T22:00:56.145927+00:00", "image_urls": ["https://tropic.ssec.wisc.edu/real-time/atlantic/winds/wg8dvg.GIF"], "etag": "\"202bf-64ae3bddf9d9b\"", "raw_metadata": {"directory_path": "https://tropic.ssec.wisc.edu/real-time/atlantic/winds", "last_modified_raw": "2026-02-15 21:44", "size_text": "129K", "size_bytes": 132096, "http_status": 200, "content_type": "image/gif", "content_length": 131775, "server": "Apache", "last_modified_http": "Sun, 15 Feb 2026 21:44:23 GMT"}, "spider_name": "cimss", "images": [{"url": "https://tropic.ssec.wisc.edu/real-time/atlantic/winds/wg8dvg.GIF", "path": "2026/02/15/21/202602152100_wg8dvg.GIF", "checksum": "e643e5baf7c00f68ce98b6ab558ac3ea", "status": "downloaded"}], "file_size_bytes": 148035, "file_format": "jpeg", "width": 900, "height": 680, "mode": "RGB", "is_animated": false, "frame_count": 1},
{"name": "wg8dlm6.GIF", "parent_url": "https://tropic.ssec.wisc.edu/real-time/atlantic/winds/", "page_title": "Index of /real-time/atlantic/winds", "source_modified": "2026-02-15T21:44:00", "observation_time": "2026-02-15T21:00:00", "fetched_at": "2026-02-15T22:00:56.145388+00:00", "image_urls": ["https://tropic.ssec.wisc.edu/real-time/atlantic/winds/wg8dlm6.GIF"], "etag": "\"2a7f4-64ae3bddf8dfb\"", "raw_metadata": {"directory_path": "https://tropic.ssec.wisc.edu/real-time/atlantic/winds", "last_modified_raw": "2026-02-15 21:44", "size_text": "170K", "size_bytes": 174080, "http_status": 200, "content_type": "image/gif", "content_length": 174068, "server": "Apache", "last_modified_http": "Sun, 15 Feb 2026 21:44:23 GMT"}, "spider_name": "cimss", "images": [{"url": "https://tropic.ssec.wisc.edu/real-time/atlantic/winds/wg8dlm6.GIF", "path": "2026/02/15/21/202602152100_wg8dlm6.GIF", "checksum": "72cd220fd9afa8d6e495425963e9838b", "status": "downloaded"}], "file_size_bytes": 242144, "file_format": "jpeg", "width": 960, "height": 680, "mode": "RGB", "is_animated": false, "frame_count": 1},
{"name": "wg8dlm5.GIF", "parent_url": "https://tropic.ssec.wisc.edu/real-time/atlantic/winds/", "page_title": "Index of /real-time/atlantic/winds", "source_modified": "2026-02-15T21:44:00", "observation_time": "2026-02-15T21:00:00", "fetched_at": "2026-02-15T22:00:56.144776+00:00", "image_urls": ["https://tropic.ssec.wisc.edu/real-time/atlantic/winds/wg8dlm5.GIF"], "etag": "\"2ac26-64ae3bdddf7bd\"", "raw_metadata": {"directory_path": "https://tropic.ssec.wisc.edu/real-time/atlantic/winds", "last_modified_raw": "2026-02-15 21:44", "size_text": "171K", "size_bytes": 175104, "http_status": 200, "content_type": "image/gif", "content_length": 175142, "server": "Apache", "last_modified_http": "Sun, 15 Feb 2026 21:44:23 GMT"}, "spider_name": "cimss", "images": [{"url": "https://tropic.ssec.wisc.edu/real-time/atlantic/winds/wg8dlm5.GIF", "path": "2026/02/15/21/202602152100_wg8dlm5.GIF", "checksum": "1f3ad9844f8b81a83d0a7d210549a474", "status": "downloaded"}], "file_size_bytes": 246720, "file_format": "jpeg", "width": 960, "height": 680, "mode": "RGB", "is_animated": false, "frame_count": 1},
{"name": "wg8dlm4.GIF", "parent_url": "https://tropic.ssec.wisc.edu/real-time/atlantic/winds/", "page_title": "Index of /real-time/atlantic/winds", "source_modified": "2026-02-15T21:44:00", "observation_time": "2026-02-15T21:00:00", "fetched_at": "2026-02-15T22:00:56.144212+00:00", "image_urls": ["https://tropic.ssec.wisc.edu/real-time/atlantic/winds/wg8dlm4.GIF"], "etag": "\"2b4cc-64ae3bdddec05\"", "raw_metadata": {"directory_path": "https://tropic.ssec.wisc.edu/real-time/atlantic/winds", "last_modified_raw": "2026-02-15 21:44", "size_text": "173K", "size_bytes": 177152, "http_status": 200, "content_type": "image/gif", "content_length": 177356, "server": "Apache", "last_modified_http": "Sun, 15 Feb 2026 21:44:23 GMT"}, "spider_name": "cimss", "images": [{"url": "https://tropic.ssec.wisc.edu/real-time/atlantic/winds/wg8dlm4.GIF", "path": "2026/02/15/21/202602152100_wg8dlm4.GIF", "checksum": "dc16caef25cbb14e59b0114c2bdfad7d", "status": "downloaded"}], "file_size_bytes": 254405, "file_format": "jpeg", "width": 960, "height": 680, "mode": "RGB", "is_animated": false, "frame_count": 1},
{"name": "wg8dlm3.GIF", "parent_url": "https://tropic.ssec.wisc.edu/real-time/atlantic/winds/", "page_title": "Index of /real-time/atlantic/winds", "source_modified": "2026-02-15T21:44:00", "observation_time": "2026-02-15T21:00:00", "fetched_at": "2026-02-15T22:00:56.143613+00:00", "image_urls": ["https://tropic.ssec.wisc.edu/real-time/atlantic/winds/wg8dlm3.GIF"], "etag": "\"2c738-64ae3bddd9de6\"", "raw_metadata": {"directory_path": "https://tropic.ssec.wisc.edu/real-time/atlantic/winds", "last_modified_raw": "2026-02-15 21:44", "size_text": "178K", "size_bytes": 182272, "http_status": 200, "content_type": "image/gif", "content_length": 182072, "server": "Apache", "last_modified_http": "Sun, 15 Feb 2026 21:44:23 GMT"}, "spider_name": "cimss", "images": [{"url": "https://tropic.ssec.wisc.edu/real-time/atlantic/winds/wg8dlm3.GIF", "path": "2026/02/15/21/202602152100_wg8dlm3.GIF", "checksum": "5814dd95118da7d1270f506151aeb9b1", "status": "downloaded"}], "file_size_bytes": 242199, "file_format": "jpeg", "width": 960, "height": 680, "mode": "RGB", "is_animated": false, "frame_count": 1},
{"name": "wg8dlm2.GIF", "parent_url": "https://tropic.ssec.wisc.edu/real-time/atlantic/winds/", "page_title": "Index of /real-time/atlantic/winds", "source_modified": "2026-02-15T21:44:00", "observation_time": "2026-02-15T21:00:00", "fetched_at": "2026-02-15T22:00:56.143062+00:00", "image_urls": ["https://tropic.ssec.wisc.edu/real-time/atlantic/winds/wg8dlm2.GIF"], "etag": "\"2dc81-64ae3bddd8e46\"", "raw_metadata": {"directory_path": "https://tropic.ssec.wisc.edu/real-time/atlantic/winds", "last_modified_raw": "2026-02-15 21:44", "size_text": "183K", "size_bytes": 187392, "http_status": 200, "content_type": "image/gif", "content_length": 187521, "server": "Apache", "last_modified_http": "Sun, 15 Feb 2026 21:44:23 GMT"}, "spider_name": "cimss", "images": [{"url": "https://tropic.ssec.wisc.edu/real-time/atlantic/winds/wg8dlm2.GIF", "path": "2026/02/15/21/202602152100_wg8dlm2.GIF", "checksum": "36f833514591fce32cd8b692fbd42f43", "status": "downloaded"}], "file_size_bytes": 234262, "file_format": "jpeg", "width": 960, "height": 680, "mode": "RGB", "is_animated": false, "frame_count": 1},
{"name": "wg8dlm1.GIF", "parent_url": "https://tropic.ssec.wisc.edu/real-time/atlantic/winds/", "page_title": "Index of /real-time/atlantic/winds", "source_modified": "2026-02-15T21:44:00", "observation_time": "2026-02-15T21:00:00", "fetched_at": "2026-02-15T22:00:56.142477+00:00", "image_urls": ["https://tropic.ssec.wisc.edu/real-time/atlantic/winds/wg8dlm1.GIF"], "etag": "\"3160a-64ae3bddd7ea6\"", "raw_metadata": {"directory_path": "https://tropic.ssec.wisc.edu/real-time/atlantic/winds", "last_modified_raw": "2026-02-15 21:44", "size_text": "198K", "size_bytes": 202752, "http_status": 200, "content_type": "image/gif", "content_length": 202250, "server": "Apache", "last_modified_http": "Sun, 15 Feb 2026 21:44:23 GMT"}, "spider_name": "cimss", "images": [{"url": "https://tropic.ssec.wisc.edu/real-time/atlantic/winds/wg8dlm1.GIF", "path": "2026/02/15/21/202602152100_wg8dlm1.GIF", "checksum": "aee767da13a0e274ed01cce4b813ec27", "status": "downloaded"}], "file_size_bytes": 229831, "file_format": "jpeg", "width": 960, "height": 680, "mode": "RGB", "is_animated": false, "frame_count": 1},
{"name": "wg8wxc.GIF", "parent_url": "https://tropic.ssec.wisc.edu/real-time/atlantic/winds/", "page_title": "Index of /real-time/atlantic/winds", "source_modified": "2026-02-15T21:44:00", "observation_time": "2026-02-15T21:00:00", "fetched_at": "2026-02-15T22:00:56.157180+00:00", "image_urls": ["https://tropic.ssec.wisc.edu/real-time/atlantic/winds/wg8wxc.GIF"], "etag": "\"2faf8-64ae3bde54e9b\"", "raw_metadata": {"directory_path": "https://tropic.ssec.wisc.edu/real-time/atlantic/winds", "last_modified_raw": "2026-02-15 21:44", "size_text": "191K", "size_bytes": 195584, "http_status": 200, "content_type": "image/gif", "content_length": 195320, "server": "Apache", "last_modified_http": "Sun, 15 Feb 2026 21:44:24 GMT"}, "spider_name": "cimss", "images": [{"url": "https://tropic.ssec.wisc.edu/real-time/atlantic/winds/wg8wxc.GIF", "path": "2026/02/15/21/202602152100_wg8wxc.GIF", "checksum": "4ee35375be64eb652a4e713f64501174", "status": "downloaded"}], "file_size_bytes": 205174, "file_format": "jpeg", "width": 960, "height": 680, "mode": "RGB", "is_animated": false, "frame_count": 1},
{"name": "wg8wvir.GIF", "parent_url": "https://tropic.ssec.wisc.edu/real-time/atlantic/winds/", "page_title": "Index of /real-time/atlantic/winds", "source_modified": "2026-02-15T21:44:00", "observation_time": "2026-02-15T21:00:00", "fetched_at": "2026-02-15T22:00:56.156678+00:00", "image_urls": ["https://tropic.ssec.wisc.edu/real-time/atlantic/winds/wg8wvir.GIF"], "etag": "\"260ab-64ae3bde3a8bd\"", "raw_metadata": {"directory_path": "https://tropic.ssec.wisc.edu/real-time/atlantic/winds", "last_modified_raw": "2026-02-15 21:44", "size_text": "152K", "size_bytes": 155648, "http_status": 200, "content_type": "image/gif", "content_length": 155819, "server": "Apache", "last_modified_http": "Sun, 15 Feb 2026 21:44:24 GMT"}, "spider_name": "cimss", "images": [{"url": "https://tropic.ssec.wisc.edu/real-time/atlantic/winds/wg8wvir.GIF", "path": "2026/02/15/21/202602152100_wg8wvir.GIF", "checksum": "793ba885c1f3a59a81f2dfbb577e9d3c", "status": "downloaded"}], "file_size_bytes": 212435, "file_format": "jpeg", "width": 900, "height": 680, "mode": "RGB", "is_animated": false, "frame_count": 1},
{"name": "wg8vor5.GIF", "parent_url": "https://tropic.ssec.wisc.edu/real-time/atlantic/winds/", "page_title": "Index of /real-time/atlantic/winds", "source_modified": "2026-02-15T21:44:00", "observation_time": "2026-02-15T21:00:00", "fetched_at": "2026-02-15T22:00:56.155955+00:00", "image_urls": ["https://tropic.ssec.wisc.edu/real-time/atlantic/winds/wg8vor5.GIF"], "etag": "\"33f5d-64ae3bde1e3a0\"", "raw_metadata": {"directory_path": "https://tropic.ssec.wisc.edu/real-time/atlantic/winds", "last_modified_raw": "2026-02-15 21:44", "size_text": "208K", "size_bytes": 212992, "http_status": 200, "content_type": "image/gif", "content_length": 212829, "server": "Apache", "last_modified_http": "Sun, 15 Feb 2026 21:44:23 GMT"}, "spider_name": "cimss", "images": [{"url": "https://tropic.ssec.wisc.edu/real-time/atlantic/winds/wg8vor5.GIF", "path": "2026/02/15/21/202602152100_wg8vor5.GIF", "checksum": "2e3ae8dc2659aa3bf6a41abf2b7c92dd", "status": "downloaded"}], "file_size_bytes": 147332, "file_format": "jpeg", "width": 960, "height": 680, "mode": "RGB", "is_animated": false, "frame_count": 1},
{"name": "wg8vor4.GIF", "parent_url": "https://tropic.ssec.wisc.edu/real-time/atlantic/winds/", "page_title": "Index of /real-time/atlantic/winds", "source_modified": "2026-02-15T21:44:00", "observation_time": "2026-02-15T21:00:00", "fetched_at": "2026-02-15T22:00:56.155460+00:00", "image_urls": ["https://tropic.ssec.wisc.edu/real-time/atlantic/winds/wg8vor4.GIF"], "etag": "\"350f9-64ae3bde1d400\"", "raw_metadata": {"directory_path": "https://tropic.ssec.wisc.edu/real-time/atlantic/winds", "last_modified_raw": "2026-02-15 21:44", "size_text": "212K", "size_bytes": 217088, "http_status": 200, "content_type": "image/gif", "content_length": 217337, "server": "Apache", "last_modified_http": "Sun, 15 Feb 2026 21:44:23 GMT"}, "spider_name": "cimss", "images": [{"url": "https://tropic.ssec.wisc.edu/real-time/atlantic/winds/wg8vor4.GIF", "path": "2026/02/15/21/202602152100_wg8vor4.GIF", "checksum": "6f94b17cb602c64f439d46c4fc6f919d", "status": "downloaded"}], "file_size_bytes": 145571, "file_format": "jpeg", "width": 960, "height": 680, "mode": "RGB", "is_animated": false, "frame_count": 1},
{"name": "wg8vor3.GIF", "parent_url": "https://tropic.ssec.wisc.edu/real-time/atlantic/winds/", "page_title": "Index of /real-time/atlantic/winds", "source_modified": "2026-02-15T21:44:00", "observation_time": "2026-02-15T21:00:00", "fetched_at": "2026-02-15T22:00:56.154951+00:00", "image_urls": ["https://tropic.ssec.wisc.edu/real-time/atlantic/winds/wg8vor3.GIF"], "etag": "\"33aae-64ae3bde1c460\"", "raw_metadata": {"directory_path": "https://tropic.ssec.wisc.edu/real-time/atlantic/winds", "last_modified_raw": "2026-02-15 21:44", "size_text": "207K", "size_bytes": 211968, "http_status": 200, "content_type": "image/gif", "content_length": 211630, "server": "Apache", "last_modified_http": "Sun, 15 Feb 2026 21:44:23 GMT"}, "spider_name": "cimss", "images": [{"url": "https://tropic.ssec.wisc.edu/real-time/atlantic/winds/wg8vor3.GIF", "path": "2026/02/15/21/202602152100_wg8vor3.GIF", "checksum": "81a51c538c0043e010696917999172c3", "status": "downloaded"}], "file_size_bytes": 142215, "file_format": "jpeg", "width": 960, "height": 680, "mode": "RGB", "is_animated": false, "frame_count": 1},
{"name": "wg8vor2.GIF", "parent_url": "https://tropic.ssec.wisc.edu/real-time/atlantic/winds/", "page_title": "Index of /real-time/atlantic/winds", "source_modified": "2026-02-15T21:44:00", "observation_time": "2026-02-15T21:00:00", "fetched_at": "2026-02-15T22:00:56.154424+00:00", "image_urls": ["https://tropic.ssec.wisc.edu/real-time/atlantic/winds/wg8vor2.GIF"], "etag": "\"35ad2-64ae3bde19968\"", "raw_metadata": {"directory_path": "https://tropic.ssec.wisc.edu/real-time/atlantic/winds", "last_modified_raw": "2026-02-15 21:44", "size_text": "215K", "size_bytes": 220160, "http_status": 200, "content_type": "image/gif", "content_length": 219858, "server": "Apache", "last_modified_http": "Sun, 15 Feb 2026 21:44:23 GMT"}, "spider_name": "cimss", "images": [{"url": "https://tropic.ssec.wisc.edu/real-time/atlantic/winds/wg8vor2.GIF", "path": "2026/02/15/21/202602152100_wg8vor2.GIF", "checksum": "32eea6130807d5629da86652f29b0be4", "status": "downloaded"}], "file_size_bytes": 139352, "file_format": "jpeg", "width": 960, "height": 680, "mode": "RGB", "is_animated": false, "frame_count": 1},
{"name": "wg8vor1.GIF", "parent_url": "https://tropic.ssec.wisc.edu/real-time/atlantic/winds/", "page_title": "Index of /real-time/atlantic/winds", "source_modified": "2026-02-15T21:44:00", "observation_time": "2026-02-15T21:00:00", "fetched_at": "2026-02-15T22:00:56.153827+00:00", "image_urls": ["https://tropic.ssec.wisc.edu/real-time/atlantic/winds/wg8vor1.GIF"], "etag": "\"2e589-64ae3bde189c8\"", "raw_metadata": {"directory_path": "https://tropic.ssec.wisc.edu/real-time/atlantic/winds", "last_modified_raw": "2026-02-15 21:44", "size_text": "185K", "size_bytes": 189440, "http_status": 200, "content_type": "image/gif", "content_length": 189833, "server": "Apache", "last_modified_http": "Sun, 15 Feb 2026 21:44:23 GMT"}, "spider_name": "cimss", "images": [{"url": "https://tropic.ssec.wisc.edu/real-time/atlantic/winds/wg8vor1.GIF", "path": "2026/02/15/21/202602152100_wg8vor1.GIF", "checksum": "d791175e23db1b661db3ef3bb651e85f", "status": "downloaded"}], "file_size_bytes": 130362, "file_format": "jpeg", "width": 960, "height": 680, "mode": "RGB", "is_animated": false, "frame_count": 1}
]