[
{"name": "wg8dvg.GIF", "parent_url": "https://tropic.ssec.wisc.edu/real-time/atlantic/winds/", "page_title": "Index of /real-time/atlantic/winds", "source_modified": "2026-01-16T12:43:00", "observation_time": "2026-01-16T12:00:00", "fetched_at": "2026-01-16T14:48:54.858241+00:00", "image_urls": ["https://tropic.ssec.wisc.edu/real-time/atlantic/winds/wg8dvg.GIF"], "etag": "\"2309b-64880b0de445c\"", "raw_metadata": {"directory_path": "https://tropic.ssec.wisc.edu/real-time/atlantic/winds", "last_modified_raw": "2026-01-16 12:43", "size_text": "140K", "size_bytes": 143360, "http_status": 200, "content_type": "image/gif", "content_length": 143515, "server": "Apache", "last_modified_http": "Fri, 16 Jan 2026 12:43:40 GMT"}, "spider_name": "cimss", "images": [{"url": "https://tropic.ssec.wisc.edu/real-time/atlantic/winds/wg8dvg.GIF", "path": "2026/01/16/12/202601161200_wg8dvg.GIF", "checksum": "c94e4a03a41f4d3faab87f9039e0db9b", "status": "cached"}], "file_size_bytes": 150866, "file_format": "jpeg", "width": 900, "height": 680, "mode": "RGB", "is_animated": false, "frame_count": 1},
{"name": "wg8dlm6.GIF", "parent_url": "https://tropic.ssec.wisc.edu/real-time/atlantic/winds/", "page_title": "Index of /real-time/atlantic/winds", "source_modified": "2026-01-16T12:43:00", "observation_time": "2026-01-16T12:00:00", "fetched_at": "2026-01-16T14:48:54.857756+00:00", "image_urls": ["https://tropic.ssec.wisc.edu/real-time/atlantic/winds/wg8dlm6.GIF"], "etag": "\"34a52-64880b0dc92c6\"", "raw_metadata": {"directory_path": "https://tropic.ssec.wisc.edu/real-time/atlantic/winds", "last_modified_raw": "2026-01-16 12:43", "size_text": "211K", "size_bytes": 216064, "http_status": 200, "content_type": "image/gif", "content_length": 215634, "server": "Apache", "last_modified_http": "Fri, 16 Jan 2026 12:43:40 GMT"}, "spider_name": "cimss", "images": [{"url": "https://tropic.ssec.wisc.edu/real-time/atlantic/winds/wg8dlm6.GIF", "path": "2026/01/16/12/202601161200_wg8dlm6.GIF", "checksum": "27c18abee35de908167871a139d841e5", "status": "cached"}], "file_size_bytes": 233591, "file_format": "jpeg", "width": 960, "height": 680, "mode": "RGB", "is_animated": false, "frame_count": 1},
{"name": "wg8dlm5.GIF", "parent_url": "https://tropic.ssec.wisc.edu/real-time/atlantic/winds/", "page_title": "Index of /real-time/atlantic/winds", "source_modified": "2026-01-16T12:43:00", "observation_time": "2026-01-16T12:00:00", "fetched_at": "2026-01-16T14:48:54.857251+00:00", "image_urls": ["https://tropic.ssec.wisc.edu/real-time/atlantic/winds/wg8dlm5.GIF"], "etag": "\"33b8e-64880b0dad961\"", "raw_metadata": {"directory_path": "https://tropic.ssec.wisc.edu/real-time/atlantic/winds", "last_modified_raw": "2026-01-16 12:43", "size_text": "207K", "size_bytes": 211968, "http_status": 200, "content_type": "image/gif", "content_length": 211854, "server": "Apache", "last_modified_http": "Fri, 16 Jan 2026 12:43:40 GMT"}, "spider_name": "cimss", "images": [{"url": "https://tropic.ssec.wisc.edu/real-time/atlantic/winds/wg8dlm5.GIF", "path": "2026/01/16/12/202601161200_wg8dlm5.GIF", "checksum": "47d21f6c6e7e5bdd1a6898a5b6e90c38", "status": "cached"}], "file_size_bytes": 245084, "file_format": "jpeg", "width": 960, "height": 680, "mode": "RGB", "is_animated": false, "frame_count": 1},
{"name": "wg8dlm4.GIF", "parent_url": "https://tropic.ssec.wisc.edu/real-time/atlantic/winds/", "page_title": "Index of /real-time/atlantic/winds", "source_modified": "2026-01-16T12:43:00", "observation_time": "2026-01-16T12:00:00", "fetched_at": "2026-01-16T14:48:54.856766+00:00", "image_urls": ["https://tropic.ssec.wisc.edu/real-time/atlantic/winds/wg8dlm4.GIF"], "etag": "\"32eb7-64880b0d93b53\"", "raw_metadata": {"directory_path": "https://tropic.ssec.wisc.edu/real-time/atlantic/winds", "last_modified_raw": "2026-01-16 12:43", "size_text": "204K", "size_bytes": 208896, "http_status": 200, "content_type": "image/gif", "content_length": 208567, "server": "Apache", "last_modified_http": "Fri, 16 Jan 2026 12:43:40 GMT"}, "spider_name": "cimss", "images": [{"url": "https://tropic.ssec.wisc.edu/real-time/atlantic/winds/wg8dlm4.GIF", "path": "2026/01/16/12/202601161200_wg8dlm4.GIF", "checksum": "34e2ff3503cc7b567779cba719ada450", "status": "cached"}], "file_size_bytes": 242987, "file_format": "jpeg", "width": 960, "height": 680, "mode": "RGB", "is_animated": false, "frame_count": 1},
{"name": "wg8dlm3.GIF", "parent_url": "https://tropic.ssec.wisc.edu/real-time/atlantic/winds/", "page_title": "Index of /real-time/atlantic/winds", "source_modified": "2026-01-16T12:43:00", "observation_time": "2026-01-16T12:00:00", "fetched_at": "2026-01-16T14:48:54.856280+00:00", "image_urls": ["https://tropic.ssec.wisc.edu/real-time/atlantic/winds/wg8dlm3.GIF"], "etag": "\"32762-64880b0d5f768\"", "raw_metadata": {"directory_path": "https://tropic.ssec.wisc.edu/real-time/atlantic/winds", "last_modified_raw": "2026-01-16 12:43", "size_text": "202K", "size_bytes": 206848, "http_status": 200, "content_type": "image/gif", "content_length": 206690, "server": "Apache", "last_modified_http": "Fri, 16 Jan 2026 12:43:40 GMT"}, "spider_name": "cimss", "images": [{"url": "https://tropic.ssec.wisc.edu/real-time/atlantic/winds/wg8dlm3.GIF", "path": "2026/01/16/12/202601161200_wg8dlm3.GIF", "checksum": "2876290db84a47655c0af0fcd9bcac77", "status": "cached"}], "file_size_bytes": 247384, "file_format": "jpeg", "width": 960, "height": 680, "mode": "RGB", "is_animated": false, "frame_count": 1},
{"name": "wg8dlm2.GIF", "parent_url": "https://tropic.ssec.wisc.edu/real-time/atlantic/winds/", "page_title": "Index of /real-time/atlantic/winds", "source_modified": "2026-01-16T12:43:00", "observation_time": "2026-01-16T12:00:00", "fetched_at": "2026-01-16T14:48:54.855778+00:00", "image_urls": ["https://tropic.ssec.wisc.edu/real-time/atlantic/winds/wg8dlm2.GIF"], "etag": "\"32b89-64880b0d4595a\"", "raw_metadata": {"directory_path": "https://tropic.ssec.wisc.edu/real-time/atlantic/winds", "last_modified_raw": "2026-01-16 12:43", "size_text": "203K", "size_bytes": 207872, "http_status": 200, "content_type": "image/gif", "content_length": 207753, "server": "Apache", "last_modified_http": "Fri, 16 Jan 2026 12:43:39 GMT"}, "spider_name": "cimss", "images": [{"url": "https://tropic.ssec.wisc.edu/real-time/atlantic/winds/wg8dlm2.GIF", "path": "2026/01/16/12/202601161200_wg8dlm2.GIF", "checksum": "78ba8a94318477c65e7958c31568b69d", "status": "cached"}], "file_size_bytes": 250945, "file_format": "jpeg", "width": 960, "height": 680, "mode": "RGB", "is_animated": false, "frame_count": 1},
{"name": "wg8dlm1.GIF", "parent_url": "https://tropic.ssec.wisc.edu/real-time/atlantic/winds/", "page_title": "Index of /real-time/atlantic/winds", "source_modified": "2026-01-16T12:43:00", "observation_time": "2026-01-16T12:00:00", "fetched_at": "2026-01-16T14:48:54.855265+00:00", "image_urls": ["https://tropic.ssec.wisc.edu/real-time/atlantic/winds/wg8dlm1.GIF"], "etag": "\"3418b-64880b0d2c31d\"", "raw_metadata": {"directory_path": "https://tropic.ssec.wisc.edu/real-time/atlantic/winds", "last_modified_raw": "2026-01-16 12:43", "size_text": "208K", "size_bytes": 212992, "http_status": 200, "content_type": "image/gif", "content_length": 213387, "server": "Apache", "last_modified_http": "Fri, 16 Jan 2026 12:43:39 GMT"}, "spider_name": "cimss", "images": [{"url": "https://tropic.ssec.wisc.edu/real-time/atlantic/winds/wg8dlm1.GIF", "path": "2026/01/16/12/202601161200_wg8dlm1.GIF", "checksum": "cb29438952487365c2a027f7a3992135", "status": "cached"}], "file_size_bytes": 254014, "file_format": "jpeg", "width": 960, "height": 680, "mode": "RGB", "is_animated": false, "frame_count": 1},
{"name": "wg8conv.GIF", "parent_url": "https://tropic.ssec.wisc.edu/real-time/atlantic/winds/", "page_title": "Index of /real-time/atlantic/winds", "source_modified": "2026-01-16T12:43:00", "observation_time": "2026-01-16T12:00:00", "fetched_at": "2026-01-16T14:48:54.854701+00:00", "image_urls": ["https://tropic.ssec.wisc.edu/real-time/atlantic/winds/wg8conv.GIF"], "etag": "\"2d6c4-64880b0cf96a1\"", "raw_metadata": {"directory_path": "https://tropic.ssec.wisc.edu/real-time/atlantic/winds", "last_modified_raw": "2026-01-16 12:43", "size_text": "182K", "size_bytes": 186368, "http_status": 200, "content_type": "image/gif", "content_length": 186052, "server": "Apache", "last_modified_http": "Fri, 16 Jan 2026 12:43:39 GMT"}, "spider_name": "cimss", "images": [{"url": "https://tropic.ssec.wisc.edu/real-time/atlantic/winds/wg8conv.GIF", "path": "2026/01/16/12/202601161200_wg8conv.GIF", "checksum": "0c00d73dea5f4eff9f4e1b2dddbc7329", "status": "cached"}], "file_size_bytes": 159705, "file_format": "jpeg", "width": 900, "height": 680, "mode": "RGB", "is_animated": false, "frame_count": 1},
{"name": "windNWATL.gif", "parent_url": "https://tropic.ssec.wisc.edu/real-time/wavetrak/domains/", "page_title": "Index of /real-time/wavetrak/domains", "source_modified": "2026-01-16T08:57:00", "observation_time": "2026-01-16T08:00:00", "fetched_at": "2026-01-16T14:48:54.828753+00:00", "image_urls": ["https://tropic.ssec.wisc.edu/real-time/wavetrak/domains/windNWATL.gif"], "etag": "\"5fd85-6487d86f76cac\"", "raw_metadata": {"directory_path": "https://tropic.ssec.wisc.edu/real-time/wavetrak/domains", "last_modified_raw": "2026-01-16 08:57", "size_text": "383K", "size_bytes": 392192, "http_status": 200, "content_type": "image/gif", "content_length": 392581, "server": "Apache", "last_modified_http": "Fri, 16 Jan 2026 08:57:12 GMT"}, "spider_name": "cimss", "images": [{"url": "https://tropic.ssec.wisc.edu/real-time/wavetrak/domains/windNWATL.gif", "path": "2026/01/16/08/202601160800_windNWATL.gif", "checksum": "4d170f8ddabf479bba94fbd090c156ad", "status": "cached"}], "file_size_bytes": 200709, "file_format": "jpeg", "width": 900, "height": 680, "mode": "RGB", "is_animated": false, "frame_count": 1},
{"name": "g16split.jpg", "parent_url": "https://tropic.ssec.wisc.edu/real-time/sal/g16split/", "page_title": "Index of /real-time/sal/g16split", "source_modified": "2026-01-16T12:30:00", "observation_time": "2026-01-16T12:00:00", "fetched_at": "2026-01-16T14:48:54.801265+00:00", "image_urls": ["https://tropic.ssec.wisc.edu/real-time/sal/g16split/g16split.jpg"], "etag": "\"98921-6488081f3e93e\"", "raw_metadata": {"directory_path": "https://tropic.ssec.wisc.edu/real-time/sal/g16split", "last_modified_raw": "2026-01-16 12:30", "size_text": "610K", "size_bytes": 624640, "http_status": 200, "content_type": "image/jpeg", "content_length": 624929, "server": "Apache", "last_modified_http": "Fri, 16 Jan 2026 12:30:33 GMT"}, "spider_name": "cimss", "images": [{"url": "https://tropic.ssec.wisc.edu/real-time/sal/g16split/g16split.jpg", "path": "2026/01/16/12/202601161200_g16split.jpg", "checksum": "921505f8cddfcf8285428a77bdde9ef0", "status": "cached"}], "file_size_bytes": 624929, "file_format": "jpeg", "width": 1542, "height": 820, "mode": "RGB", "is_animated": false, "frame_count": 1},
{"name": "wg8wxc.GIF", "parent_url": "https://tropic.ssec.wisc.edu/real-time/atlantic/winds/", "page_title": "Index of /real-time/atlantic/winds", "source_modified": "2026-01-16T12:43:00", "observation_time": "2026-01-16T12:00:00", "fetched_at": "2026-01-16T14:48:54.869631+00:00", "image_urls": ["https://tropic.ssec.wisc.edu/real-time/atlantic/winds/wg8wxc.GIF"], "etag": "\"35208-64880b0ec1b40\"", "raw_metadata": {"directory_path": "https://tropic.ssec.wisc.edu/real-time/atlantic/winds", "last_modified_raw": "2026-01-16 12:43", "size_text": "213K", "size_bytes": 218112, "http_status": 200, "content_type": "image/gif", "content_length": 217608, "server": "Apache", "last_modified_http": "Fri, 16 Jan 2026 12:43:41 GMT"}, "spider_name": "cimss", "images": [{"url": "https://tropic.ssec.wisc.edu/real-time/atlantic/winds/wg8wxc.GIF", "path": "2026/01/16/12/202601161200_wg8wxc.GIF", "checksum": "8a15a8ef6e7ff77ffddd568c23df0149", "status": "cached"}], "file_size_bytes": 216962, "file_format": "jpeg", "width": 960, "height": 680, "mode": "RGB", "is_animated": false, "frame_count": 1},
{"name": "wg8wvir.GIF", "parent_url": "https://tropic.ssec.wisc.edu/real-time/atlantic/winds/", "page_title": "Index of /real-time/atlantic/winds", "source_modified": "2026-01-16T12:43:00", "observation_time": "2026-01-16T12:00:00", "fetched_at": "2026-01-16T14:48:54.869150+00:00", "image_urls": ["https://tropic.ssec.wisc.edu/real-time/atlantic/winds/wg8wvir.GIF"], "etag": "\"28cbc-64880b0ec0ba0\"", "raw_metadata": {"directory_path": "https://tropic.ssec.wisc.edu/real-time/atlantic/winds", "last_modified_raw": "2026-01-16 12:43", "size_text": "163K", "size_bytes": 166912, "http_status": 200, "content_type": "image/gif", "content_length": 167100, "server": "Apache", "last_modified_http": "Fri, 16 Jan 2026 12:43:41 GMT"}, "spider_name": "cimss", "images": [{"url": "https://tropic.ssec.wisc.edu/real-time/atlantic/winds/wg8wvir.GIF", "path": "2026/01/16/12/202601161200_wg8wvir.GIF", "checksum": "538914f5097df9505f4dc423b36495ff", "status": "cached"}], "file_size_bytes": 205640, "file_format": "jpeg", "width": 900, "height": 680, "mode": "RGB", "is_animated": false, "frame_count": 1},
{"name": "wg8vor5.GIF", "parent_url": "https://tropic.ssec.wisc.edu/real-time/atlantic/winds/", "page_title": "Index of /real-time/atlantic/winds", "source_modified": "2026-01-16T12:43:00", "observation_time": "2026-01-16T12:00:00", "fetched_at": "2026-01-16T14:48:54.868563+00:00", "image_urls": ["https://tropic.ssec.wisc.edu/real-time/atlantic/winds/wg8vor5.GIF"], "etag": "\"35c6f-64880b0e73d2f\"", "raw_metadata": {"directory_path": "https://tropic.ssec.wisc.edu/real-time/atlantic/winds", "last_modified_raw": "2026-01-16 12:43", "size_text": "215K", "size_bytes": 220160, "http_status": 200, "content_type": "image/gif", "content_length": 220271, "server": "Apache", "last_modified_http": "Fri, 16 Jan 2026 12:43:41 GMT"}, "spider_name": "cimss", "images": [{"url": "https://tropic.ssec.wisc.edu/real-time/atlantic/winds/wg8vor5.GIF", "path": "2026/01/16/12/202601161200_wg8vor5.GIF", "checksum": "e08a02563a3ffdc581fec122dbcfa233", "status": "cached"}], "file_size_bytes": 146347, "file_format": "jpeg", "width": 960, "height": 680, "mode": "RGB", "is_animated": false, "frame_count": 1},
{"name": "wg8vor4.GIF", "parent_url": "https://tropic.ssec.wisc.edu/real-time/atlantic/winds/", "page_title": "Index of /real-time/atlantic/winds", "source_modified": "2026-01-16T12:43:00", "observation_time": "2026-01-16T12:00:00", "fetched_at": "2026-01-16T14:48:54.868099+00:00", "image_urls": ["https://tropic.ssec.wisc.edu/real-time/atlantic/winds/wg8vor4.GIF"], "etag": "\"37e23-64880b0e72d8f\"", "raw_metadata": {"directory_path": "https://tropic.ssec.wisc.edu/real-time/atlantic/winds", "last_modified_raw": "2026-01-16 12:43", "size_text": "224K", "size_bytes": 229376, "http_status": 200, "content_type": "image/gif", "content_length": 228899, "server": "Apache", "last_modified_http": "Fri, 16 Jan 2026 12:43:41 GMT"}, "spider_name": "cimss", "images": [{"url": "https://tropic.ssec.wisc.edu/real-time/atlantic/winds/wg8vor4.GIF", "path": "2026/01/16/12/202601161200_wg8vor4.GIF", "checksum": "b1a333ab1729fb40ae6d39747dcfe98b", "status": "cached"}], "file_size_bytes": 143943, "file_format": "jpeg", "width": 960, "height": 680, "mode": "RGB", "is_animated": false, "frame_count": 1},
{"name": "wg8vor3.GIF", "parent_url": "https://tropic.ssec.wisc.edu/real-time/atlantic/winds/", "page_title": "Index of /real-time/atlantic/winds", "source_modified": "2026-01-16T12:43:00", "observation_time": "2026-01-16T12:00:00", "fetched_at": "2026-01-16T14:48:54.867619+00:00", "image_urls": ["https://tropic.ssec.wisc.edu/real-time/atlantic/winds/wg8vor3.GIF"], "etag": "\"36661-64880b0e57812\"", "raw_metadata": {"directory_path": "https://tropic.ssec.wisc.edu/real-time/atlantic/winds", "last_modified_raw": "2026-01-16 12:43", "size_text": "218K", "size_bytes": 223232, "http_status": 200, "content_type": "image/gif", "content_length": 222817, "server": "Apache", "last_modified_http": "Fri, 16 Jan 2026 12:43:41 GMT"}, "spider_name": "cimss", "images": [{"url": "https://tropic.ssec.wisc.edu/real-time/atlantic/winds/wg8vor3.GIF", "path": "2026/01/16/12/202601161200_wg8vor3.GIF", "checksum": "cc1957ca336f57222e2a622a072fdcea", "status": "cached"}], "file_size_bytes": 142746, "file_format": "jpeg", "width": 960, "height": 680, "mode": "RGB", "is_animated": false, "frame_count": 1},
{"name": "wg8vor2.GIF", "parent_url": "https://tropic.ssec.wisc.edu/real-time/atlantic/winds/", "page_title": "Index of /real-time/atlantic/winds", "source_modified": "2026-01-16T12:43:00", "observation_time": "2026-01-16T12:00:00", "fetched_at": "2026-01-16T14:48:54.867139+00:00", "image_urls": ["https://tropic.ssec.wisc.edu/real-time/atlantic/winds/wg8vor2.GIF"], "etag": "\"37d80-64880b0e3ce4c\"", "raw_metadata": {"directory_path": "https://tropic.ssec.wisc.edu/real-time/atlantic/winds", "last_modified_raw": "2026-01-16 12:43", "size_text": "223K", "size_bytes": 228352, "http_status": 200, "content_type": "image/gif", "content_length": 228736, "server": "Apache", "last_modified_http": "Fri, 16 Jan 2026 12:43:40 GMT"}, "spider_name": "cimss", "images": [{"url": "https://tropic.ssec.wisc.edu/real-time/atlantic/winds/wg8vor2.GIF", "path": "2026/01/16/12/202601161200_wg8vor2.GIF", "checksum": "8d17bed2e22f07f715fa4f238c265841", "status": "cached"}], "file_size_bytes": 138684, "file_format": "jpeg", "width": 960, "height": 680, "mode": "RGB", "is_animated": false, "frame_count": 1},
{"name": "wg8vor1.GIF", "parent_url": "https://tropic.ssec.wisc.edu/real-time/atlantic/winds/", "page_title": "Index of /real-time/atlantic/winds", "source_modified": "2026-01-16T12:43:00", "observation_time": "2026-01-16T12:00:00", "fetched_at": "2026-01-16T14:48:54.866621+00:00", "image_urls": ["https://tropic.ssec.wisc.edu/real-time/atlantic/winds/wg8vor1.GIF"], "etag": "\"33597-64880b0e3beac\"", "raw_metadata": {"directory_path": "https://tropic.ssec.wisc.edu/real-time/atlantic/winds", "last_modified_raw": "2026-01-16 12:43", "size_text": "205K", "size_bytes": 209920, "http_status": 200, "content_type": "image/gif", "content_length": 210327, "server": "Apache", "last_modified_http": "Fri, 16 Jan 2026 12:43:40 GMT"}, "spider_name": "cimss", "images": [{"url": "https://tropic.ssec.wisc.edu/real-time/atlantic/winds/wg8vor1.GIF", "path": "2026/01/16/12/202601161200_wg8vor1.GIF", "checksum": "122ee149d823096d98ba245b1dc07044", "status": "cached"}], "file_size_bytes": 134000, "file_format": "jpeg", "width": 960, "height": 680, "mode": "RGB", "is_animated": false, "frame_count": 1},
{"name": "wg8vor.GIF", "parent_url": "https://tropic.ssec.wisc.edu/real-time/atlantic/winds/", "page_title": "Index of /real-time/atlantic/winds", "source_modified": "2026-01-16T12:43:00", "observation_time": "2026-01-16T12:00:00", "fetched_at": "2026-01-16T14:48:54.866246+00:00", "image_urls": ["https://tropic.ssec.wisc.edu/real-time/atlantic/winds/wg8vor.GIF"], "etag": "\"37e23-64880b0e8db3d\"", "raw_metadata": {"directory_path": "https://tropic.ssec.wisc.edu/real-time/atlantic/winds", "last_modified_raw": "2026-01-16 12:43", "size_text": "224K", "size_bytes": 229376, "http_status": 200, "content_type": "image/gif", "content_length": 228899, "server": "Apache", "last_modified_http": "Fri, 16 Jan 2026 12:43:41 GMT"}, "spider_name": "cimss", "images": [{"url": "https://tropic.ssec.wisc.edu/real-time/atlantic/winds/wg8vor.GIF", "path": "2026/01/16/12/202601161200_wg8vor.GIF", "checksum": "b1a333ab1729fb40ae6d39747dcfe98b", "status": "cached"}], "file_size_bytes": 143943, "file_format": "jpeg", "width": 960, "height": 680, "mode": "RGB", "is_animated": false, "frame_count": 1},
{"name": "wg8sht.GIF", "parent_url": "https://tropic.ssec.wisc.edu/real-time/atlantic/winds/", "page_title": "Index of /real-time/atlantic/winds", "source_modified": "2026-01-16T12:43:00", "observation_time": "2026-01-16T12:00:00", "fetched_at": "2026-01-16T14:48:54.861541+00:00", "image_urls": ["https://tropic.ssec.wisc.edu/real-time/atlantic/winds/wg8sht.GIF"], "etag": "\"3711b-64880b0e35d05\"", "raw_metadata": {"directory_path": "https://tropic.ssec.wisc.edu/real-time/atlantic/winds", "last_modified_raw": "2026-01-16 12:43", "size_text": "220K", "size_bytes": 225280, "http_status": 200, "content_type": "image/gif", "content_length": 225563, "server": "Apache", "last_modified_http": "Fri, 16 Jan 2026 12:43:40 GMT"}, "spider_name": "cimss", "images": [{"url": "https://tropic.ssec.wisc.edu/real-time/atlantic/winds/wg8sht.GIF", "path": "2026/01/16/12/202601161200_wg8sht.GIF", "checksum": "90eff93e383fb74fc6c737d955bef734", "status": "cached"}], "file_size_bytes": 230944, "file_format": "jpeg", "width": 960, "height": 680, "mode": "RGB", "is_animated": false, "frame_count": 1},
{"name": "wg8shr.GIF", "parent_url": "https://tropic.ssec.wisc.edu/real-time/atlantic/winds/", "page_title": "Index of /real-time/atlantic/winds", "source_modified": "2026-01-16T12:43:00", "observation_time": "2026-01-16T12:00:00", "fetched_at": "2026-01-16T14:48:54.861037+00:00", "image_urls": ["https://tropic.ssec.wisc.edu/real-time/atlantic/winds/wg8shr.GIF"], "etag": "\"27b90-64880b0e1ab6f\"", "raw_metadata": {"directory_path": "https://tropic.ssec.wisc.edu/real-time/atlantic/winds", "last_modified_raw": "2026-01-16 12:43", "size_text": "159K", "size_bytes": 162816, "http_status": 200, "content_type": "image/gif", "content_length": 162704, "server": "Apache", "last_modified_http": "Fri, 16 Jan 2026 12:43:40 GMT"}, "spider_name": "cimss", "images": [{"url": "https://tropic.ssec.wisc.edu/real-time/atlantic/winds/wg8shr.GIF", "path": "2026/01/16/12/202601161200_wg8shr.GIF", "checksum": "c2adf1e12e7bb6b1ad8d78978cad7d8a", "status": "cached"}], "file_size_bytes": 206886, "file_format": "jpeg", "width": 900, "height": 680, "mode": "RGB", "is_animated": false, "frame_count": 1},
{"name": "wg8midshr.GIF", "parent_url": "https://tropic.ssec.wisc.edu/real-time/atlantic/winds/", "page_title": "Index of /real-time/atlantic/winds", "source_modified": "2026-01-16T12:43:00", "observation_time": "2026-01-16T12:00:00", "fetched_at": "2026-01-16T14:48:54.860542+00:00", "image_urls": ["https://tropic.ssec.wisc.edu/real-time/atlantic/winds/wg8midshr.GIF"], "etag": "\"40ada-64880b0e19bcf\"", "raw_metadata": {"directory_path": "https://tropic.ssec.wisc.edu/real-time/atlantic/winds", "last_modified_raw": "2026-01-16 12:43", "size_text": "259K", "size_bytes": 265216, "http_status": 200, "content_type": "image/gif", "content_length": 264922, "server": "Apache", "last_modified_http": "Fri, 16 Jan 2026 12:43:40 GMT"}, "spider_name": "cimss", "images": [{"url": "https://tropic.ssec.wisc.edu/real-time/atlantic/winds/wg8midshr.GIF", "path": "2026/01/16/12/202601161200_wg8midshr.GIF", "checksum": "470c906bff81235456ef5aa702ebd297", "status": "cached"}], "file_size_bytes": 197120, "file_format": "jpeg", "width": 960, "height": 680, "mode": "RGB", "is_animated": false, "frame_count": 1},
{"name": "wg8ir.GIF", "parent_url": "https://tropic.ssec.wisc.edu/real-time/atlantic/winds/", "page_title": "Index of /real-time/atlantic/winds", "source_modified": "2026-01-16T12:43:00", "observation_time": "2026-01-16T12:00:00", "fetched_at": "2026-01-16T14:48:54.860038+00:00", "image_urls": ["https://tropic.ssec.wisc.edu/real-time/atlantic/winds/wg8ir.GIF"], "etag": "\"32405-64880b0e18c2f\"", "raw_metadata": {"directory_path": "https://tropic.ssec.wisc.edu/real-time/atlantic/winds", "last_modified_raw": "2026-01-16 12:43", "size_text": "201K", "size_bytes": 205824, "http_status": 200, "content_type": "image/gif", "content_length": 205829, "server": "Apache", "last_modified_http": "Fri, 16 Jan 2026 12:43:40 GMT"}, "spider_name": "cimss", "images": [{"url": "https://tropic.ssec.wisc.edu/real-time/atlantic/winds/wg8ir.GIF", "path": "2026/01/16/12/202601161200_wg8ir.GIF", "checksum": "723b9da628568158eac513c590f9f1a5", "status": "cached"}], "file_size_bytes": 207061, "file_format": "jpeg", "width": 900, "height": 680, "mode": "RGB", "is_animated": false, "frame_count": 1}
]